librus/__init__.py
librus-0.0.15.dist-info/LICENSE
librus-0.0.15.dist-info/METADATA
librus-0.0.15.dist-info/WHEEL
librus-0.0.15.dist-info/top_level.txt
librus-0.0.15.dist-info/zip-safe
librus-0.0.15.dist-info/RECORD
