Metadata-Version: 2.1
Name: librus
Version: 0.0.15
Summary: Librus Synergia API
Home-page: https://github.com/findepi/librus-api-python
Classifier: Programming Language :: Python :: 3
Classifier: Programming Language :: Python :: 3.7
Classifier: License :: OSI Approved :: Apache Software License
Requires-Python: >=3
License-File: LICENSE
Requires-Dist: requests-html
